neutron_vpnaas/__init__.py
neutron_vpnaas/_i18n.py
neutron_vpnaas/opts.py
neutron_vpnaas/version.py
neutron_vpnaas/agent/__init__.py
neutron_vpnaas/agent/ovn/__init__.py
neutron_vpnaas/agent/ovn/vpn/__init__.py
neutron_vpnaas/agent/ovn/vpn/agent.py
neutron_vpnaas/agent/ovn/vpn/ovsdb.py
neutron_vpnaas/api/rpc/agentnotifiers/vpn_rpc_agent_api.py
neutron_vpnaas/cmd/eventlet/__init__.py
neutron_vpnaas/cmd/eventlet/ovn_agent.py
neutron_vpnaas/db/__init__.py
neutron_vpnaas/db/migration/__init__.py
neutron_vpnaas/db/migration/alembic_migrations/README
neutron_vpnaas/db/migration/alembic_migrations/__init__.py
neutron_vpnaas/db/migration/alembic_migrations/env.py
neutron_vpnaas/db/migration/alembic_migrations/script.py.mako
neutron_vpnaas/db/migration/alembic_migrations/versions/3ea02b2a773e_add_index_tenant_id.py
neutron_vpnaas/db/migration/alembic_migrations/versions/CONTRACT_HEAD
neutron_vpnaas/db/migration/alembic_migrations/versions/EXPAND_HEAD
neutron_vpnaas/db/migration/alembic_migrations/versions/kilo_release.py
neutron_vpnaas/db/migration/alembic_migrations/versions/start_neutron_vpnaas.py
neutron_vpnaas/db/migration/alembic_migrations/versions/2023.2/expand/22e0145ac80b_add_vpn_gateway_port.py
neutron_vpnaas/db/migration/alembic_migrations/versions/2023.2/expand/3b739d6906cf_vpn_scheduler.py
neutron_vpnaas/db/migration/alembic_migrations/versions/2025.1/expand/b18aab30fddc_add_more_ciphers.py
neutron_vpnaas/db/migration/alembic_migrations/versions/liberty/contract/2c82e782d734_drop_tenant_id_in_cisco_csr_identifier_.py
neutron_vpnaas/db/migration/alembic_migrations/versions/liberty/contract/333dfd6afaa2_populate_vpn_service_table_fields.py
neutron_vpnaas/db/migration/alembic_migrations/versions/liberty/contract/56893333aa52_fix_identifier_map_fk.py
neutron_vpnaas/db/migration/alembic_migrations/versions/liberty/expand/24f28869838b_add_fields_to_vpn_service_table.py
neutron_vpnaas/db/migration/alembic_migrations/versions/liberty/expand/30018084ed99_initial.py
neutron_vpnaas-27.0.0.dist-info/AUTHORS
neutron_vpnaas-27.0.0.dist-info/LICENSE
neutron_vpnaas-27.0.0.dist-info/METADATA
neutron_vpnaas-27.0.0.dist-info/WHEEL
neutron_vpnaas-27.0.0.dist-info/entry_points.txt
neutron_vpnaas-27.0.0.dist-info/pbr.json
neutron_vpnaas-27.0.0.dist-info/top_level.txt
neutron_vpnaas-27.0.0.dist-info/RECORD
